<?xml version="1.0" encoding="UTF-8"?>
<rdf:RDF	xmlns:rdf="http://www.w3.org/1999/02/22-rdf-syntax-ns#"
	xmlns:cim="http://iec.ch/TC57/2010/CIM-schema-cim15#"
	xmlns:ftn="http://www.ftnydro.com/CIM15/2010/extension#">
<!-- generated by: 'CIMET' application -->
<!-- ACLineSegment -->
	<cim:ACLineSegment rdf:ID="ACLS_133769420">
		<cim:IdentifiedObject.mRID>AC1</cim:IdentifiedObject.mRID>
		<cim:IdentifiedObject.name>ACLine</cim:IdentifiedObject.name>
		<cim:IdentifiedObject.aliasName>ACLine1</cim:IdentifiedObject.aliasName>
		<cim:ACLineSegment.b0ch>0.1</cim:ACLineSegment.b0ch>
		<cim:ACLineSegment.bch>0.2</cim:ACLineSegment.bch>
		<cim:ACLineSegment.g0ch>0.3</cim:ACLineSegment.g0ch>
		<cim:ACLineSegment.gch>0.4</cim:ACLineSegment.gch>
		<cim:ACLineSegment.r>0.5</cim:ACLineSegment.r>
		<cim:ACLineSegment.r0>0.6</cim:ACLineSegment.r0>
		<cim:ACLineSegment.x>0.7</cim:ACLineSegment.x>
		<cim:ACLineSegment.x0>0.8</cim:ACLineSegment.x0>
	</cim:ACLineSegment>
	<cim:ACLineSegment rdf:ID="ACLS_133769421">
		<cim:IdentifiedObject.mRID>T2</cim:IdentifiedObject.mRID>
		<cim:IdentifiedObject.name>T2</cim:IdentifiedObject.name>
		<cim:IdentifiedObject.aliasName>Terminal2</cim:IdentifiedObject.aliasName>
		<cim:ACLineSegment.b0ch>0.11</cim:ACLineSegment.b0ch>
		<cim:ACLineSegment.bch>0.11</cim:ACLineSegment.bch>
		<cim:ACLineSegment.g0ch>0.11</cim:ACLineSegment.g0ch>
		<cim:ACLineSegment.gch>0.11</cim:ACLineSegment.gch>
		<cim:ACLineSegment.r>0.11</cim:ACLineSegment.r>
		<cim:ACLineSegment.r0>0.11</cim:ACLineSegment.r0>
		<cim:ACLineSegment.x>0.11</cim:ACLineSegment.x>
		<cim:ACLineSegment.x0>0.11</cim:ACLineSegment.x0>
	</cim:ACLineSegment>
	<!-- ACLineSegmentPhase -->
	<cim:ACLineSegmentPhase rdf:ID="ACLSP_637494416619123964">
		<cim:IdentifiedObject.mRID>1</cim:IdentifiedObject.mRID>
		<cim:IdentifiedObject.name>jedan</cim:IdentifiedObject.name>
		<cim:IdentifiedObject.aliasName>prvi</cim:IdentifiedObject.aliasName>
		<cim:ACLineSegmentPhase.phase>SinglePhaseKind.A</cim:ACLineSegmentPhase.phase>
		<cim:ACLineSegmentPhase.ACLineSegment rdf:resource="#ACLS_133769420"/>
	</cim:ACLineSegmentPhase>
	<!-- MutualCoupling -->
	<cim:MutualCoupling rdf:ID="MC_637494418057429001">
		<cim:IdentifiedObject.mRID>MC1</cim:IdentifiedObject.mRID>
		<cim:IdentifiedObject.name>MC1</cim:IdentifiedObject.name>
		<cim:IdentifiedObject.aliasName>MutualCoupling1</cim:IdentifiedObject.aliasName>
		<cim:MutualCoupling.b0ch>0.3</cim:MutualCoupling.b0ch>
		<cim:MutualCoupling.distance11>0.3</cim:MutualCoupling.distance11>
		<cim:MutualCoupling.distance12>0.3</cim:MutualCoupling.distance12>
		<cim:MutualCoupling.distance21>0.3</cim:MutualCoupling.distance21>
		<cim:MutualCoupling.distance22>0.3</cim:MutualCoupling.distance22>
		<cim:MutualCoupling.g0ch>0.3</cim:MutualCoupling.g0ch>
		<cim:MutualCoupling.r0>0.3</cim:MutualCoupling.r0>
		<cim:MutualCoupling.x0>0.3</cim:MutualCoupling.x0>
		<cim:MutualCoupling.First_Terminal rdf:resource="#T_637497850442793700"/>
	</cim:MutualCoupling>
	<!-- Terminal -->
	<cim:Terminal rdf:ID="T_637497850442793700">
		<cim:IdentifiedObject.mRID>T1</cim:IdentifiedObject.mRID>
		<cim:IdentifiedObject.name>T1</cim:IdentifiedObject.name>
		<cim:IdentifiedObject.aliasName>Terminal1</cim:IdentifiedObject.aliasName>
		<cim:Terminal.connected>true</cim:Terminal.connected>
		<cim:Terminal.phases>PhaseCode.ABC</cim:Terminal.phases>
		<cim:Terminal.sequenceNumber>13</cim:Terminal.sequenceNumber>
		<cim:Terminal.ConductingEquipment rdf:resource="#ACLS_133769420"/>
	</cim:Terminal>
</rdf:RDF>